.DS_Store
zipmigo/__init__.py
zipmigo/download.py
zipmigo/list_dir.py
zipmigo/unzip.py
zipmigo/zipmigo.py
zipmigo-1.1.0.dist-info/LICENSE.txt
zipmigo-1.1.0.dist-info/METADATA
zipmigo-1.1.0.dist-info/WHEEL
zipmigo-1.1.0.dist-info/top_level.txt
zipmigo-1.1.0.dist-info/RECORD
