Metadata-Version: 2.1
Name: zipmigo
Version: 1.1.0
Summary: Simple package to download & unzip archives within notebooks.
Home-page: https://github.com/kaszklar/zipmigo
Author: Katie Aszklar
Author-email: kea2143@columbia.edu
License: UNKNOWN
Platform: UNKNOWN
Classifier: Programming Language :: Python :: 3
Classifier: License :: OSI Approved :: MIT License
Classifier: Operating System :: OS Independent
Requires-Python: >=3.6
Requires-Dist: tqdm (>=4.38)
Requires-Dist: requests (>=2.22.0)
